ChuxuezhedeMingxiangshu/Dockerfile
ChuxuezhedeMingxiangshu/README.md
ChuxuezhedeMingxiangshu/__init__.py
ChuxuezhedeMingxiangshu/__main__.py
ChuxuezhedeMingxiangshu/file.epub
ChuxuezhedeMingxiangshu/index.html
ChuxuezhedeMingxiangshu/css/__init__.py
ChuxuezhedeMingxiangshu/css/annotations.css
ChuxuezhedeMingxiangshu/css/main.css
ChuxuezhedeMingxiangshu/css/normalize.css
ChuxuezhedeMingxiangshu/css/popup.css
ChuxuezhedeMingxiangshu/font/__init__.py
ChuxuezhedeMingxiangshu/font/fontello.eot
ChuxuezhedeMingxiangshu/font/fontello.svg
ChuxuezhedeMingxiangshu/font/fontello.ttf
ChuxuezhedeMingxiangshu/font/fontello.woff
ChuxuezhedeMingxiangshu/img/__init__.py
ChuxuezhedeMingxiangshu/img/annotator-glyph-sprite.png
ChuxuezhedeMingxiangshu/img/annotator-icon-sprite.png
ChuxuezhedeMingxiangshu/img/apple-touch-icon.png
ChuxuezhedeMingxiangshu/img/cancelfullscreen.png
ChuxuezhedeMingxiangshu/img/close.png
ChuxuezhedeMingxiangshu/img/fullscreen.png
ChuxuezhedeMingxiangshu/img/loader.gif
ChuxuezhedeMingxiangshu/img/menu-icon.png
ChuxuezhedeMingxiangshu/img/save.png
ChuxuezhedeMingxiangshu/img/saved.png
ChuxuezhedeMingxiangshu/img/settings-s.png
ChuxuezhedeMingxiangshu/img/settings.png
ChuxuezhedeMingxiangshu/img/star.png
ChuxuezhedeMingxiangshu/js/__init__.py
ChuxuezhedeMingxiangshu/js/epub.js
ChuxuezhedeMingxiangshu/js/epub.min.js
ChuxuezhedeMingxiangshu/js/epub.min.map
ChuxuezhedeMingxiangshu/js/hooks.min.js
ChuxuezhedeMingxiangshu/js/hooks.min.map
ChuxuezhedeMingxiangshu/js/reader.js
ChuxuezhedeMingxiangshu/js/reader.js.map
ChuxuezhedeMingxiangshu/js/reader.min.js
ChuxuezhedeMingxiangshu/js/reader.min.map
ChuxuezhedeMingxiangshu/js/hooks/__init__.py
ChuxuezhedeMingxiangshu/js/hooks/extensions/__init__.py
ChuxuezhedeMingxiangshu/js/hooks/extensions/highlight.js
ChuxuezhedeMingxiangshu/js/libs/__init__.py
ChuxuezhedeMingxiangshu/js/libs/jquery.min.js
ChuxuezhedeMingxiangshu/js/libs/localforage.min.js
ChuxuezhedeMingxiangshu/js/libs/screenfull.js
chuxuezhede_mingxiangshu-2022.10.9.1.dist-info/METADATA
chuxuezhede_mingxiangshu-2022.10.9.1.dist-info/WHEEL
chuxuezhede_mingxiangshu-2022.10.9.1.dist-info/entry_points.txt
chuxuezhede_mingxiangshu-2022.10.9.1.dist-info/top_level.txt
chuxuezhede_mingxiangshu-2022.10.9.1.dist-info/RECORD
